django_plugin_blog/__init__.py
django_plugin_blog/admin.py
django_plugin_blog/apps.py
django_plugin_blog/models.py
django_plugin_blog/views.py
django_plugin_blog/migrations/0001_initial.py
django_plugin_blog/migrations/__init__.py
django_plugin_blog/templates/django_plugin_blog/archive.html
django_plugin_blog/templates/django_plugin_blog/base.html
django_plugin_blog/templates/django_plugin_blog/entry.html
django_plugin_blog/templates/django_plugin_blog/index.html
django_plugin_blog/templates/django_plugin_blog/tag.html
django_plugin_blog/templates/django_plugin_blog/year.html
django_plugin_blog-0.1.1.dist-info/LICENSE
django_plugin_blog-0.1.1.dist-info/METADATA
django_plugin_blog-0.1.1.dist-info/WHEEL
django_plugin_blog-0.1.1.dist-info/entry_points.txt
django_plugin_blog-0.1.1.dist-info/top_level.txt
django_plugin_blog-0.1.1.dist-info/RECORD
