Metadata-Version: 2.1
Name: django-plugin-blog
Version: 0.1.1
Summary: A simple blog implemented as a DJP plugin
Author: Simon Willison
License: Apache-2.0
Project-URL: Homepage, https://github.com/simonw/django-plugin-blog
Project-URL: Changelog, https://github.com/simonw/django-plugin-blog/releases
Project-URL: Issues, https://github.com/simonw/django-plugin-blog/issues
Project-URL: CI, https://github.com/simonw/django-plugin-blog/actions
Classifier: License :: OSI Approved :: Apache Software License
License-File: LICENSE
Requires-Dist: django
Requires-Dist: Markdown
Requires-Dist: djp >=0.1
Provides-Extra: test
Requires-Dist: pytest ; extra == 'test'
Requires-Dist: pytest-django ; extra == 'test'
